oggm_marine_terminating/__init__.py
oggm_marine_terminating/aux_funcs.py
oggm_marine_terminating/flux_model.py
oggm_marine_terminating-0.1.1.dist-info/licenses/LICENSE.txt
oggm_marine_terminating-0.1.1.dist-info/METADATA
oggm_marine_terminating-0.1.1.dist-info/WHEEL
oggm_marine_terminating-0.1.1.dist-info/top_level.txt
oggm_marine_terminating-0.1.1.dist-info/RECORD
