Metadata-Version: 2.4
Name: oggm_marine_terminating
Version: 0.1.1
Summary: Enhanced modeling of marine-terminating glaciers for OGGM
Home-page: https://github.com/MuhammadShafeeque/Enhanced-Modeling-Marine-Terminating-Glaciers
Author: Muhammad Shafeeque
Author-email: Muhammad Shafeeque <shafeequ@uni-bremen.de>
License-Expression: BSD-3-Clause
Project-URL: Homepage, https://github.com/MuhammadShafeeque/Enhanced-Modeling-Marine-Terminating-Glaciers
Project-URL: Bug Tracker, https://github.com/MuhammadShafeeque/Enhanced-Modeling-Marine-Terminating-Glaciers/issues
Classifier: Development Status :: 3 - Alpha
Classifier: Intended Audience :: Science/Research
Classifier: Programming Language :: Python :: 3
Classifier: Programming Language :: Python :: 3.7
Classifier: Programming Language :: Python :: 3.8
Classifier: Programming Language :: Python :: 3.9
Classifier: Topic :: Scientific/Engineering
Classifier: Topic :: Scientific/Engineering :: Atmospheric Science
Requires-Python: >=3.8
License-File: LICENSE.txt
Requires-Dist: oggm==1.5.3
Requires-Dist: numpy>=1.17.0
Requires-Dist: scipy>=1.3.0
Requires-Dist: pandas>=1.0.0
Requires-Dist: matplotlib>=3.1.0
Dynamic: author
Dynamic: home-page
Dynamic: license-file
Dynamic: requires-python
